{
  "domain": "aldi.us",
  "records": [
    "0 issue \"amazon.com\"",
    "0 issue \"amazontrust.com\"",
    "0 issue \"awstrust.com\"",
    "0 issue \"digicert.com\"",
    "0 issue \"letsencrypt.org\"",
    "0 issue \"pki.goog\"",
    "0 issue \"sectigo.com\"",
    "0 issuewild \"amazon.com\"",
    "9 issue \"amazonaws.com\""
  ],
  "issue": [
    "amazon.com",
    "amazonaws.com",
    "amazontrust.com",
    "awstrust.com",
    "digicert.com",
    "letsencrypt.org",
    "pki.goog",
    "sectigo.com"
  ],
  "issuewild": [
    "amazon.com"
  ],
  "iodef": [],
  "issuemail": [],
  "contactemail": [],
  "contactphone": []
}