{
  "domain": "mckesson.com",
  "records": [
    "0 issue \"amazon.com\"",
    "0 issue \"digicert.com\"",
    "0 issue \"globalsign.com\"",
    "0 issue \"identrust.com\"",
    "0 issue \"letsencrypt.org\"",
    "0 issue \"pki.goog\"",
    "0 issuemail \"digicert.com\"",
    "0 issuemail \"identrust.com\""
  ],
  "issue": [
    "amazon.com",
    "digicert.com",
    "globalsign.com",
    "identrust.com",
    "letsencrypt.org",
    "pki.goog"
  ],
  "issuewild": [],
  "iodef": [],
  "issuemail": [
    "digicert.com",
    "identrust.com"
  ],
  "contactemail": [],
  "contactphone": []
}